pip_sync_faster/__init__.py
pip_sync_faster/__main__.py
pip_sync_faster/cli.py
pip_sync_faster/sync.py
pip_sync_faster-0.0.5.dist-info/LICENSE
pip_sync_faster-0.0.5.dist-info/METADATA
pip_sync_faster-0.0.5.dist-info/WHEEL
pip_sync_faster-0.0.5.dist-info/entry_points.txt
pip_sync_faster-0.0.5.dist-info/top_level.txt
pip_sync_faster-0.0.5.dist-info/RECORD
