Metadata-Version: 2.2
Name: pip-sync-faster
Version: 0.0.5
Summary: A wrapper that makes pip-sync faster.
Home-page: https://github.com/hypothesis/pip-sync-faster
Project-URL: Bug Tracker, https://github.com/hypothesis/pip-sync-faster/issues
Project-URL: Changelog, https://github.com/hypothesis/pip-sync-faster/releases
Classifier: Programming Language :: Python :: 3
Classifier: License :: OSI Approved :: BSD License
Classifier: Intended Audience :: Developers
Requires-Python: >=3.9
License-File: LICENSE
Requires-Dist: pip-tools
Requires-Dist: importlib_metadata; python_version < "3.8."
